{
  "color-space-for-untagged-svg-colors" : "display-p3",
  "fill" : {
    "solid" : "display-p3:0.92920,0.93164,0.94141,1.00000"
  },
  "groups" : [
    {
      "layers" : [

      ],
      "shadow" : {
        "kind" : "neutral",
        "opacity" : 0.5
      },
      "translucency" : {
        "enabled" : true,
        "value" : 0.5
      }
    },
    {
      "layers" : [
        {
          "blend-mode" : "normal",
          "fill" : {
            "solid" : "display-p3:0.08038,0.09192,0.10266,1.00000"
          },
          "glass" : true,
          "image-name" : "tmono-01.svg",
          "name" : "tmono-01",
          "position" : {
            "scale" : 0.75,
            "translation-in-points" : [
              0,
              0
            ]
          }
        }
      ],
      "shadow" : {
        "kind" : "neutral",
        "opacity" : 0.5
      },
      "translucency" : {
        "enabled" : true,
        "value" : 0.5
      }
    },
    {
      "layers" : [

      ],
      "shadow" : {
        "kind" : "neutral",
        "opacity" : 0.5
      },
      "translucency" : {
        "enabled" : true,
        "value" : 0.5
      }
    }
  ],
  "supported-platforms" : {
    "squares" : "shared"
  }
}